SNN/__init__.py
SNN/event.py
SNN/datasets/__init__.py
SNN/datasets/fCifar10_dvs.py
SNN/datasets/fEventBase.py
SNN/datasets/fMnist_dvs.py
SNN/datasets/fN_caltech101.py
SNN/datasets/fN_cars.py
SNN/network/__init__.py
SNN/network/layer.py
SNN/network/model.py
SNN/network/node.py
SNN/network/resnet.py
SNN/network/vgg.py
SNN/utils/__init__.py
SNN/utils/loader.py
SNN/utils/loss.py
SNN/utils/transformer.py
SNN/utils/utils.py
EasySNN-0.1.2.dist-info/METADATA
EasySNN-0.1.2.dist-info/WHEEL
EasySNN-0.1.2.dist-info/top_level.txt
EasySNN-0.1.2.dist-info/RECORD
